[
  {
    "transactionId": "TXN100001",
    "accountNumber": "123456789012",
    "accountHolderName": "Rishikesh Negi",
    "transactionType": "credit",
    "amount": 60000.0,
    "date": "2025-01-01T09:00:00Z",
    "description": "Monthly salary",
    "category": "salary",
    "balanceAfterTransaction": 210000.0,
    "paymentMethod": "bank_transfer",
    "status": "completed",
    "senderDetails": {
      "name": "Tech Corp Solutions",
      "bankName": "HDFC Bank",
      "accountNumber": "998877665544",
      "ifsc": "HDFC0001234"
    }
  },
  {
    "transactionId": "TXN100006",
    "accountNumber": "123456789012",
    "accountHolderName": "Rishikesh Negi",
    "transactionType": "debit",
    "amount": 5340.0,
    "date": "2025-01-04T00:00:00Z",
    "description": "Myntra order",
    "category": "shopping",
    "balanceAfterTransaction": 204660.0,
    "paymentMethod": "bank_transfer",
    "status": "completed",
    "beneficiaryDetails": {
      "name": "Myntra",
      "bankName": "Unknown",
      "accountNumber": "N/A",
      "ifsc": "N/A"
    }
  },
  {
    "transactionId": "TXN100003",
    "accountNumber": "123456789012",
    "accountHolderName": "Rishikesh Negi",
    "transactionType": "debit",
    "amount": 4891.0,
    "date": "2025-01-10T00:00:00Z",
    "description": "Reliance Fresh",
    "category": "groceries",
    "balanceAfterTransaction": 199769.0,
    "paymentMethod": "upi",
    "status": "completed",
    "beneficiaryDetails": {
      "name": "Reliance",
      "bankName": "Unknown",
      "accountNumber": "N/A",
      "ifsc": "N/A"
    }
  },
  {
    "transactionId": "TXN100002",
    "accountNumber": "123456789012",
    "accountHolderName": "Rishikesh Negi",
    "transactionType": "debit",
    "amount": 8000.0,
    "date": "2025-01-10T11:00:00Z",
    "description": "Monthly house rent",
    "category": "rent",
    "balanceAfterTransaction": 191769.0,
    "paymentMethod": "bank_transfer",
    "status": "completed",
    "beneficiaryDetails": {
      "name": "Suresh Kumar (Landlord)",
      "bankName": "SBI",
      "accountNumber": "554433221100",
      "ifsc": "SBIN0000123"
    }
  },
  {
    "transactionId": "TXN100005",
    "accountNumber": "123456789012",
    "accountHolderName": "Rishikesh Negi",
    "transactionType": "debit",
    "amount": 10250.0,
    "date": "2025-01-20T00:00:00Z",
    "description": "Myntra order",
    "category": "shopping",
    "balanceAfterTransaction": 181519.0,
    "paymentMethod": "cheque",
    "status": "completed",
    "beneficiaryDetails": {
      "name": "Myntra",
      "bankName": "Unknown",
      "accountNumber": "N/A",
      "ifsc": "N/A"
    }
  },
  {
    "transactionId": "TXN100004",
    "accountNumber": "123456789012",
    "accountHolderName": "Rishikesh Negi",
    "transactionType": "debit",
    "amount": 3441.0,
    "date": "2025-01-28T00:00:00Z",
    "description": "BigBasket",
    "category": "groceries",
    "balanceAfterTransaction": 178078.0,
    "paymentMethod": "upi",
    "status": "completed",
    "beneficiaryDetails": {
      "name": "BigBasket",
      "bankName": "Unknown",
      "accountNumber": "N/A",
      "ifsc": "N/A"
    }
  },
  {
    "transactionId": "TXN100007",
    "accountNumber": "123456789012",
    "accountHolderName": "Rishikesh Negi",
    "transactionType": "credit",
    "amount": 60000.0,
    "date": "2025-02-01T09:00:00Z",
    "description": "Monthly salary",
    "category": "salary",
    "balanceAfterTransaction": 238078.0,
    "paymentMethod": "bank_transfer",
    "status": "completed",
    "senderDetails": {
      "name": "Tech Corp Solutions",
      "bankName": "HDFC Bank",
      "accountNumber": "998877665544",
      "ifsc": "HDFC0001234"
    }
  },
  {
    "transactionId": "TXN100009",
    "accountNumber": "123456789012",
    "accountHolderName": "Rishikesh Negi",
    "transactionType": "credit",
    "amount": 1503.0,
    "date": "2025-02-05T00:00:00Z",
    "description": "Dividend payout - Equity",
    "category": "dividend",
    "balanceAfterTransaction": 239581.0,
    "paymentMethod": "upi",
    "status": "completed",
    "senderDetails": {
      "name": "NSDL / CDSL",
      "bankName": "RBI",
      "accountNumber": "000011112222",
      "ifsc": "RBIS0000001"
    }
  },
  {
    "transactionId": "TXN100008",
    "accountNumber": "123456789012",
    "accountHolderName": "Rishikesh Negi",
    "transactionType": "debit",
    "amount": 8000.0,
    "date": "2025-02-09T11:00:00Z",
    "description": "Monthly house rent",
    "category": "rent",
    "balanceAfterTransaction": 231581.0,
    "paymentMethod": "bank_transfer",
    "status": "completed",
    "beneficiaryDetails": {
      "name": "Suresh Kumar (Landlord)",
      "bankName": "SBI",
      "accountNumber": "554433221100",
      "ifsc": "SBIN0000123"
    }
  },
  {
    "transactionId": "TXN100011",
    "accountNumber": "123456789012",
    "accountHolderName": "Rishikesh Negi",
    "transactionType": "debit",
    "amount": 5713.0,
    "date": "2025-02-13T00:00:00Z",
    "description": "Petrol pump refill",
    "category": "transit",
    "balanceAfterTransaction": 225868.0,
    "paymentMethod": "bank_transfer",
    "status": "completed",
    "beneficiaryDetails": {
      "name": "Petrol",
      "bankName": "Unknown",
      "accountNumber": "N/A",
      "ifsc": "N/A"
    }
  },
  {
    "transactionId": "TXN100013",
    "accountNumber": "123456789012",
    "accountHolderName": "Rishikesh Negi",
    "transactionType": "debit",
    "amount": 1457.0,
    "date": "2025-02-20T00:00:00Z",
    "description": "Uber ride",
    "category": "transit",
    "balanceAfterTransaction": 224411.0,
    "paymentMethod": "cheque",
    "status": "completed",
    "beneficiaryDetails": {
      "name": "Uber",
      "bankName": "Unknown",
      "accountNumber": "N/A",
      "ifsc": "N/A"
    }
  },
  {
    "transactionId": "TXN100010",
    "accountNumber": "123456789012",
    "accountHolderName": "Rishikesh Negi",
    "transactionType": "debit",
    "amount": 477.0,
    "date": "2025-02-22T00:00:00Z",
    "description": "iCloud Storage",
    "category": "subscription",
    "balanceAfterTransaction": 223934.0,
    "paymentMethod": "upi",
    "status": "completed",
    "beneficiaryDetails": {
      "name": "iCloud",
      "bankName": "Unknown",
      "accountNumber": "N/A",
      "ifsc": "N/A"
    }
  },
  {
    "transactionId": "TXN100012",
    "accountNumber": "123456789012",
    "accountHolderName": "Rishikesh Negi",
    "transactionType": "credit",
    "amount": 1642.0,
    "date": "2025-02-23T00:00:00Z",
    "description": "Dividend payout - Equity",
    "category": "dividend",
    "balanceAfterTransaction": 225576.0,
    "paymentMethod": "bank_transfer",
    "status": "completed",
    "senderDetails": {
      "name": "NSDL / CDSL",
      "bankName": "RBI",
      "accountNumber": "000011112222",
      "ifsc": "RBIS0000001"
    }
  },
  {
    "transactionId": "TXN100014",
    "accountNumber": "123456789012",
    "accountHolderName": "Rishikesh Negi",
    "transactionType": "credit",
    "amount": 60000.0,
    "date": "2025-03-01T09:00:00Z",
    "description": "Monthly salary",
    "category": "salary",
    "balanceAfterTransaction": 285576.0,
    "paymentMethod": "bank_transfer",
    "status": "completed",
    "senderDetails": {
      "name": "Tech Corp Solutions",
      "bankName": "HDFC Bank",
      "accountNumber": "998877665544",
      "ifsc": "HDFC0001234"
    }
  },
  {
    "transactionId": "TXN100019",
    "accountNumber": "123456789012",
    "accountHolderName": "Rishikesh Negi",
    "transactionType": "debit",
    "amount": 8632.0,
    "date": "2025-03-05T00:00:00Z",
    "description": "BigBasket",
    "category": "groceries",
    "balanceAfterTransaction": 276944.0,
    "paymentMethod": "cheque",
    "status": "completed",
    "beneficiaryDetails": {
      "name": "BigBasket",
      "bankName": "Unknown",
      "accountNumber": "N/A",
      "ifsc": "N/A"
    }
  },
  {
    "transactionId": "TXN100015",
    "accountNumber": "123456789012",
    "accountHolderName": "Rishikesh Negi",
    "transactionType": "debit",
    "amount": 8000.0,
    "date": "2025-03-05T11:00:00Z",
    "description": "Monthly house rent",
    "category": "rent",
    "balanceAfterTransaction": 268944.0,
    "paymentMethod": "bank_transfer",
    "status": "completed",
    "beneficiaryDetails": {
      "name": "Suresh Kumar (Landlord)",
      "bankName": "SBI",
      "accountNumber": "554433221100",
      "ifsc": "SBIN0000123"
    }
  },
  {
    "transactionId": "TXN100016",
    "accountNumber": "123456789012",
    "accountHolderName": "Rishikesh Negi",
    "transactionType": "debit",
    "amount": 10824.0,
    "date": "2025-03-06T00:00:00Z",
    "description": "Amazon.in",
    "category": "shopping",
    "balanceAfterTransaction": 258120.0,
    "paymentMethod": "upi",
    "status": "completed",
    "beneficiaryDetails": {
      "name": "Amazon.in",
      "bankName": "Unknown",
      "accountNumber": "N/A",
      "ifsc": "N/A"
    }
  },
  {
    "transactionId": "TXN100020",
    "accountNumber": "123456789012",
    "accountHolderName": "Rishikesh Negi",
    "transactionType": "debit",
    "amount": 10600.0,
    "date": "2025-03-08T00:00:00Z",
    "description": "Reliance Fresh",
    "category": "groceries",
    "balanceAfterTransaction": 247520.0,
    "paymentMethod": "upi",
    "status": "completed",
    "beneficiaryDetails": {
      "name": "Reliance",
      "bankName": "Unknown",
      "accountNumber": "N/A",
      "ifsc": "N/A"
    }
  },
  {
    "transactionId": "TXN100018",
    "accountNumber": "123456789012",
    "accountHolderName": "Rishikesh Negi",
    "transactionType": "debit",
    "amount": 542.0,
    "date": "2025-03-10T00:00:00Z",
    "description": "Spotify Premium",
    "category": "subscription",
    "balanceAfterTransaction": 246978.0,
    "paymentMethod": "bank_transfer",
    "status": "completed",
    "beneficiaryDetails": {
      "name": "Spotify",
      "bankName": "Unknown",
      "accountNumber": "N/A",
      "ifsc": "N/A"
    }
  },
  {
    "transactionId": "TXN100017",
    "accountNumber": "123456789012",
    "accountHolderName": "Rishikesh Negi",
    "transactionType": "debit",
    "amount": 9746.0,
    "date": "2025-03-24T00:00:00Z",
    "description": "IndiGo flight booking",
    "category": "transit",
    "balanceAfterTransaction": 237232.0,
    "paymentMethod": "upi",
    "status": "completed",
    "beneficiaryDetails": {
      "name": "IndiGo",
      "bankName": "Unknown",
      "accountNumber": "N/A",
      "ifsc": "N/A"
    }
  },
  {
    "transactionId": "TXN100024",
    "accountNumber": "123456789012",
    "accountHolderName": "Rishikesh Negi",
    "transactionType": "debit",
    "amount": 14141.0,
    "date": "2025-04-02T00:00:00Z",
    "description": "Mobile Recharge",
    "category": "bill",
    "balanceAfterTransaction": 223091.0,
    "paymentMethod": "upi",
    "status": "completed",
    "beneficiaryDetails": {
      "name": "Mobile",
      "bankName": "Unknown",
      "accountNumber": "N/A",
      "ifsc": "N/A"
    }
  },
  {
    "transactionId": "TXN100021",
    "accountNumber": "123456789012",
    "accountHolderName": "Rishikesh Negi",
    "transactionType": "credit",
    "amount": 60000.0,
    "date": "2025-04-04T09:00:00Z",
    "description": "Monthly salary",
    "category": "salary",
    "balanceAfterTransaction": 283091.0,
    "paymentMethod": "bank_transfer",
    "status": "completed",
    "senderDetails": {
      "name": "Tech Corp Solutions",
      "bankName": "HDFC Bank",
      "accountNumber": "998877665544",
      "ifsc": "HDFC0001234"
    }
  },
  {
    "transactionId": "TXN100022",
    "accountNumber": "123456789012",
    "accountHolderName": "Rishikesh Negi",
    "transactionType": "debit",
    "amount": 8000.0,
    "date": "2025-04-07T11:00:00Z",
    "description": "Monthly house rent",
    "category": "rent",
    "balanceAfterTransaction": 275091.0,
    "paymentMethod": "bank_transfer",
    "status": "completed",
    "beneficiaryDetails": {
      "name": "Suresh Kumar (Landlord)",
      "bankName": "SBI",
      "accountNumber": "554433221100",
      "ifsc": "SBIN0000123"
    }
  },
  {
    "transactionId": "TXN100023",
    "accountNumber": "123456789012",
    "accountHolderName": "Rishikesh Negi",
    "transactionType": "debit",
    "amount": 2291.0,
    "date": "2025-04-08T00:00:00Z",
    "description": "Nike Store",
    "category": "shopping",
    "balanceAfterTransaction": 272800.0,
    "paymentMethod": "cheque",
    "status": "completed",
    "beneficiaryDetails": {
      "name": "Nike",
      "bankName": "Unknown",
      "accountNumber": "N/A",
      "ifsc": "N/A"
    }
  },
  {
    "transactionId": "TXN100026",
    "accountNumber": "123456789012",
    "accountHolderName": "Rishikesh Negi",
    "transactionType": "debit",
    "amount": 6634.0,
    "date": "2025-04-17T00:00:00Z",
    "description": "iCloud Storage",
    "category": "subscription",
    "balanceAfterTransaction": 266166.0,
    "paymentMethod": "bank_transfer",
    "status": "completed",
    "beneficiaryDetails": {
      "name": "iCloud",
      "bankName": "Unknown",
      "accountNumber": "N/A",
      "ifsc": "N/A"
    }
  },
  {
    "transactionId": "TXN100027",
    "accountNumber": "123456789012",
    "accountHolderName": "Rishikesh Negi",
    "transactionType": "debit",
    "amount": 14397.0,
    "date": "2025-04-23T00:00:00Z",
    "description": "Zerodha fund add",
    "category": "investment",
    "balanceAfterTransaction": 251769.0,
    "paymentMethod": "cheque",
    "status": "completed",
    "beneficiaryDetails": {
      "name": "Zerodha",
      "bankName": "Unknown",
      "accountNumber": "N/A",
      "ifsc": "N/A"
    }
  },
  {
    "transactionId": "TXN100025",
    "accountNumber": "123456789012",
    "accountHolderName": "Rishikesh Negi",
    "transactionType": "debit",
    "amount": 2750.0,
    "date": "2025-04-28T00:00:00Z",
    "description": "Amazon.in",
    "category": "shopping",
    "balanceAfterTransaction": 249019.0,
    "paymentMethod": "bank_transfer",
    "status": "completed",
    "beneficiaryDetails": {
      "name": "Amazon.in",
      "bankName": "Unknown",
      "accountNumber": "N/A",
      "ifsc": "N/A"
    }
  },
  {
    "transactionId": "TXN100028",
    "accountNumber": "123456789012",
    "accountHolderName": "Rishikesh Negi",
    "transactionType": "debit",
    "amount": 10625.0,
    "date": "2025-04-28T00:00:00Z",
    "description": "Zerodha fund add",
    "category": "investment",
    "balanceAfterTransaction": 238394.0,
    "paymentMethod": "cheque",
    "status": "completed",
    "beneficiaryDetails": {
      "name": "Zerodha",
      "bankName": "Unknown",
      "accountNumber": "N/A",
      "ifsc": "N/A"
    }
  },
  {
    "transactionId": "TXN100029",
    "accountNumber": "123456789012",
    "accountHolderName": "Rishikesh Negi",
    "transactionType": "credit",
    "amount": 60000.0,
    "date": "2025-05-03T09:00:00Z",
    "description": "Monthly salary",
    "category": "salary",
    "balanceAfterTransaction": 298394.0,
    "paymentMethod": "bank_transfer",
    "status": "completed",
    "senderDetails": {
      "name": "Tech Corp Solutions",
      "bankName": "HDFC Bank",
      "accountNumber": "998877665544",
      "ifsc": "HDFC0001234"
    }
  },
  {
    "transactionId": "TXN100030",
    "accountNumber": "123456789012",
    "accountHolderName": "Rishikesh Negi",
    "transactionType": "debit",
    "amount": 8000.0,
    "date": "2025-05-05T11:00:00Z",
    "description": "Monthly house rent",
    "category": "rent",
    "balanceAfterTransaction": 290394.0,
    "paymentMethod": "bank_transfer",
    "status": "completed",
    "beneficiaryDetails": {
      "name": "Suresh Kumar (Landlord)",
      "bankName": "SBI",
      "accountNumber": "554433221100",
      "ifsc": "SBIN0000123"
    }
  },
  {
    "transactionId": "TXN100032",
    "accountNumber": "123456789012",
    "accountHolderName": "Rishikesh Negi",
    "transactionType": "debit",
    "amount": 11939.0,
    "date": "2025-05-06T00:00:00Z",
    "description": "Swiggy delivery",
    "category": "food",
    "balanceAfterTransaction": 278455.0,
    "paymentMethod": "cheque",
    "status": "completed",
    "beneficiaryDetails": {
      "name": "Swiggy",
      "bankName": "Unknown",
      "accountNumber": "N/A",
      "ifsc": "N/A"
    }
  },
  {
    "transactionId": "TXN100034",
    "accountNumber": "123456789012",
    "accountHolderName": "Rishikesh Negi",
    "transactionType": "debit",
    "amount": 2132.0,
    "date": "2025-05-15T00:00:00Z",
    "description": "Zomato order",
    "category": "food",
    "balanceAfterTransaction": 276323.0,
    "paymentMethod": "cheque",
    "status": "completed",
    "beneficiaryDetails": {
      "name": "Zomato",
      "bankName": "Unknown",
      "accountNumber": "N/A",
      "ifsc": "N/A"
    }
  },
  {
    "transactionId": "TXN100031",
    "accountNumber": "123456789012",
    "accountHolderName": "Rishikesh Negi",
    "transactionType": "debit",
    "amount": 1644.0,
    "date": "2025-05-20T00:00:00Z",
    "description": "Spotify Premium",
    "category": "subscription",
    "balanceAfterTransaction": 274679.0,
    "paymentMethod": "bank_transfer",
    "status": "completed",
    "beneficiaryDetails": {
      "name": "Spotify",
      "bankName": "Unknown",
      "accountNumber": "N/A",
      "ifsc": "N/A"
    }
  },
  {
    "transactionId": "TXN100033",
    "accountNumber": "123456789012",
    "accountHolderName": "Rishikesh Negi",
    "transactionType": "debit",
    "amount": 1704.0,
    "date": "2025-05-27T00:00:00Z",
    "description": "iCloud Storage",
    "category": "subscription",
    "balanceAfterTransaction": 272975.0,
    "paymentMethod": "upi",
    "status": "completed",
    "beneficiaryDetails": {
      "name": "iCloud",
      "bankName": "Unknown",
      "accountNumber": "N/A",
      "ifsc": "N/A"
    }
  },
  {
    "transactionId": "TXN100035",
    "accountNumber": "123456789012",
    "accountHolderName": "Rishikesh Negi",
    "transactionType": "credit",
    "amount": 60000.0,
    "date": "2025-06-05T09:00:00Z",
    "description": "Monthly salary",
    "category": "salary",
    "balanceAfterTransaction": 332975.0,
    "paymentMethod": "bank_transfer",
    "status": "completed",
    "senderDetails": {
      "name": "Tech Corp Solutions",
      "bankName": "HDFC Bank",
      "accountNumber": "998877665544",
      "ifsc": "HDFC0001234"
    }
  },
  {
    "transactionId": "TXN100039",
    "accountNumber": "123456789012",
    "accountHolderName": "Rishikesh Negi",
    "transactionType": "debit",
    "amount": 5269.0,
    "date": "2025-06-06T00:00:00Z",
    "description": "Netflix monthly",
    "category": "subscription",
    "balanceAfterTransaction": 327706.0,
    "paymentMethod": "upi",
    "status": "completed",
    "beneficiaryDetails": {
      "name": "Netflix",
      "bankName": "Unknown",
      "accountNumber": "N/A",
      "ifsc": "N/A"
    }
  },
  {
    "transactionId": "TXN100041",
    "accountNumber": "123456789012",
    "accountHolderName": "Rishikesh Negi",
    "transactionType": "debit",
    "amount": 12280.0,
    "date": "2025-06-06T00:00:00Z",
    "description": "Spotify Premium",
    "category": "subscription",
    "balanceAfterTransaction": 315426.0,
    "paymentMethod": "upi",
    "status": "completed",
    "beneficiaryDetails": {
      "name": "Spotify",
      "bankName": "Unknown",
      "accountNumber": "N/A",
      "ifsc": "N/A"
    }
  },
  {
    "transactionId": "TXN100036",
    "accountNumber": "123456789012",
    "accountHolderName": "Rishikesh Negi",
    "transactionType": "debit",
    "amount": 8000.0,
    "date": "2025-06-07T11:00:00Z",
    "description": "Monthly house rent",
    "category": "rent",
    "balanceAfterTransaction": 307426.0,
    "paymentMethod": "bank_transfer",
    "status": "completed",
    "beneficiaryDetails": {
      "name": "Suresh Kumar (Landlord)",
      "bankName": "SBI",
      "accountNumber": "554433221100",
      "ifsc": "SBIN0000123"
    }
  },
  {
    "transactionId": "TXN100037",
    "accountNumber": "123456789012",
    "accountHolderName": "Rishikesh Negi",
    "transactionType": "debit",
    "amount": 4500.0,
    "date": "2025-06-15T14:00:00Z",
    "description": "Personal loan EMI",
    "category": "installment",
    "balanceAfterTransaction": 302926.0,
    "paymentMethod": "bank_transfer",
    "status": "completed",
    "beneficiaryDetails": {
      "name": "Bajaj Finance",
      "bankName": "Axis Bank",
      "accountNumber": "332211998877",
      "ifsc": "UTIB0000456"
    }
  },
  {
    "transactionId": "TXN100040",
    "accountNumber": "123456789012",
    "accountHolderName": "Rishikesh Negi",
    "transactionType": "debit",
    "amount": 10977.0,
    "date": "2025-06-18T00:00:00Z",
    "description": "Electricity Bill",
    "category": "bill",
    "balanceAfterTransaction": 291949.0,
    "paymentMethod": "cheque",
    "status": "completed",
    "beneficiaryDetails": {
      "name": "Electricity",
      "bankName": "Unknown",
      "accountNumber": "N/A",
      "ifsc": "N/A"
    }
  },
  {
    "transactionId": "TXN100038",
    "accountNumber": "123456789012",
    "accountHolderName": "Rishikesh Negi",
    "transactionType": "debit",
    "amount": 8010.0,
    "date": "2025-06-24T00:00:00Z",
    "description": "Broadband Bill",
    "category": "bill",
    "balanceAfterTransaction": 283939.0,
    "paymentMethod": "cheque",
    "status": "completed",
    "beneficiaryDetails": {
      "name": "Broadband",
      "bankName": "Unknown",
      "accountNumber": "N/A",
      "ifsc": "N/A"
    }
  },
  {
    "transactionId": "TXN100048",
    "accountNumber": "123456789012",
    "accountHolderName": "Rishikesh Negi",
    "transactionType": "debit",
    "amount": 3694.0,
    "date": "2025-07-02T00:00:00Z",
    "description": "Dinner at Social",
    "category": "food",
    "balanceAfterTransaction": 280245.0,
    "paymentMethod": "bank_transfer",
    "status": "completed",
    "beneficiaryDetails": {
      "name": "Dinner",
      "bankName": "Unknown",
      "accountNumber": "N/A",
      "ifsc": "N/A"
    }
  },
  {
    "transactionId": "TXN100042",
    "accountNumber": "123456789012",
    "accountHolderName": "Rishikesh Negi",
    "transactionType": "credit",
    "amount": 60000.0,
    "date": "2025-07-02T09:00:00Z",
    "description": "Monthly salary",
    "category": "salary",
    "balanceAfterTransaction": 340245.0,
    "paymentMethod": "bank_transfer",
    "status": "completed",
    "senderDetails": {
      "name": "Tech Corp Solutions",
      "bankName": "HDFC Bank",
      "accountNumber": "998877665544",
      "ifsc": "HDFC0001234"
    }
  },
  {
    "transactionId": "TXN100043",
    "accountNumber": "123456789012",
    "accountHolderName": "Rishikesh Negi",
    "transactionType": "debit",
    "amount": 8000.0,
    "date": "2025-07-06T11:00:00Z",
    "description": "Monthly house rent",
    "category": "rent",
    "balanceAfterTransaction": 332245.0,
    "paymentMethod": "bank_transfer",
    "status": "completed",
    "beneficiaryDetails": {
      "name": "Suresh Kumar (Landlord)",
      "bankName": "SBI",
      "accountNumber": "554433221100",
      "ifsc": "SBIN0000123"
    }
  },
  {
    "transactionId": "TXN100046",
    "accountNumber": "123456789012",
    "accountHolderName": "Rishikesh Negi",
    "transactionType": "debit",
    "amount": 999.0,
    "date": "2025-07-09T00:00:00Z",
    "description": "Cafe coffee day",
    "category": "food",
    "balanceAfterTransaction": 331246.0,
    "paymentMethod": "upi",
    "status": "completed",
    "beneficiaryDetails": {
      "name": "Cafe",
      "bankName": "Unknown",
      "accountNumber": "N/A",
      "ifsc": "N/A"
    }
  },
  {
    "transactionId": "TXN100044",
    "accountNumber": "123456789012",
    "accountHolderName": "Rishikesh Negi",
    "transactionType": "debit",
    "amount": 4500.0,
    "date": "2025-07-15T14:00:00Z",
    "description": "Personal loan EMI",
    "category": "installment",
    "balanceAfterTransaction": 326746.0,
    "paymentMethod": "bank_transfer",
    "status": "completed",
    "beneficiaryDetails": {
      "name": "Bajaj Finance",
      "bankName": "Axis Bank",
      "accountNumber": "332211998877",
      "ifsc": "UTIB0000456"
    }
  },
  {
    "transactionId": "TXN100047",
    "accountNumber": "123456789012",
    "accountHolderName": "Rishikesh Negi",
    "transactionType": "credit",
    "amount": 1366.0,
    "date": "2025-07-19T00:00:00Z",
    "description": "Dividend payout - Equity",
    "category": "dividend",
    "balanceAfterTransaction": 328112.0,
    "paymentMethod": "upi",
    "status": "completed",
    "senderDetails": {
      "name": "NSDL / CDSL",
      "bankName": "RBI",
      "accountNumber": "000011112222",
      "ifsc": "RBIS0000001"
    }
  },
  {
    "transactionId": "TXN100045",
    "accountNumber": "123456789012",
    "accountHolderName": "Rishikesh Negi",
    "transactionType": "debit",
    "amount": 8464.0,
    "date": "2025-07-21T00:00:00Z",
    "description": "Reliance Fresh",
    "category": "groceries",
    "balanceAfterTransaction": 319648.0,
    "paymentMethod": "bank_transfer",
    "status": "completed",
    "beneficiaryDetails": {
      "name": "Reliance",
      "bankName": "Unknown",
      "accountNumber": "N/A",
      "ifsc": "N/A"
    }
  },
  {
    "transactionId": "TXN100053",
    "accountNumber": "123456789012",
    "accountHolderName": "Rishikesh Negi",
    "transactionType": "credit",
    "amount": 1937.0,
    "date": "2025-08-01T00:00:00Z",
    "description": "Dividend payout - Equity",
    "category": "dividend",
    "balanceAfterTransaction": 321585.0,
    "paymentMethod": "bank_transfer",
    "status": "completed",
    "senderDetails": {
      "name": "NSDL / CDSL",
      "bankName": "RBI",
      "accountNumber": "000011112222",
      "ifsc": "RBIS0000001"
    }
  },
  {
    "transactionId": "TXN100049",
    "accountNumber": "123456789012",
    "accountHolderName": "Rishikesh Negi",
    "transactionType": "credit",
    "amount": 60000.0,
    "date": "2025-08-04T09:00:00Z",
    "description": "Monthly salary",
    "category": "salary",
    "balanceAfterTransaction": 381585.0,
    "paymentMethod": "bank_transfer",
    "status": "completed",
    "senderDetails": {
      "name": "Tech Corp Solutions",
      "bankName": "HDFC Bank",
      "accountNumber": "998877665544",
      "ifsc": "HDFC0001234"
    }
  },
  {
    "transactionId": "TXN100050",
    "accountNumber": "123456789012",
    "accountHolderName": "Rishikesh Negi",
    "transactionType": "debit",
    "amount": 8000.0,
    "date": "2025-08-07T11:00:00Z",
    "description": "Monthly house rent",
    "category": "rent",
    "balanceAfterTransaction": 373585.0,
    "paymentMethod": "bank_transfer",
    "status": "completed",
    "beneficiaryDetails": {
      "name": "Suresh Kumar (Landlord)",
      "bankName": "SBI",
      "accountNumber": "554433221100",
      "ifsc": "SBIN0000123"
    }
  },
  {
    "transactionId": "TXN100054",
    "accountNumber": "123456789012",
    "accountHolderName": "Rishikesh Negi",
    "transactionType": "debit",
    "amount": 1418.0,
    "date": "2025-08-09T00:00:00Z",
    "description": "Reliance Fresh",
    "category": "groceries",
    "balanceAfterTransaction": 372167.0,
    "paymentMethod": "cheque",
    "status": "completed",
    "beneficiaryDetails": {
      "name": "Reliance",
      "bankName": "Unknown",
      "accountNumber": "N/A",
      "ifsc": "N/A"
    }
  },
  {
    "transactionId": "TXN100051",
    "accountNumber": "123456789012",
    "accountHolderName": "Rishikesh Negi",
    "transactionType": "debit",
    "amount": 4500.0,
    "date": "2025-08-15T14:00:00Z",
    "description": "Personal loan EMI",
    "category": "installment",
    "balanceAfterTransaction": 367667.0,
    "paymentMethod": "bank_transfer",
    "status": "completed",
    "beneficiaryDetails": {
      "name": "Bajaj Finance",
      "bankName": "Axis Bank",
      "accountNumber": "332211998877",
      "ifsc": "UTIB0000456"
    }
  },
  {
    "transactionId": "TXN100052",
    "accountNumber": "123456789012",
    "accountHolderName": "Rishikesh Negi",
    "transactionType": "debit",
    "amount": 2887.0,
    "date": "2025-08-18T00:00:00Z",
    "description": "Zomato order",
    "category": "food",
    "balanceAfterTransaction": 364780.0,
    "paymentMethod": "bank_transfer",
    "status": "completed",
    "beneficiaryDetails": {
      "name": "Zomato",
      "bankName": "Unknown",
      "accountNumber": "N/A",
      "ifsc": "N/A"
    }
  },
  {
    "transactionId": "TXN100055",
    "accountNumber": "123456789012",
    "accountHolderName": "Rishikesh Negi",
    "transactionType": "credit",
    "amount": 60000.0,
    "date": "2025-09-04T09:00:00Z",
    "description": "Monthly salary",
    "category": "salary",
    "balanceAfterTransaction": 424780.0,
    "paymentMethod": "bank_transfer",
    "status": "completed",
    "senderDetails": {
      "name": "Tech Corp Solutions",
      "bankName": "HDFC Bank",
      "accountNumber": "998877665544",
      "ifsc": "HDFC0001234"
    }
  },
  {
    "transactionId": "TXN100058",
    "accountNumber": "123456789012",
    "accountHolderName": "Rishikesh Negi",
    "transactionType": "debit",
    "amount": 4722.0,
    "date": "2025-09-06T00:00:00Z",
    "description": "Broadband Bill",
    "category": "bill",
    "balanceAfterTransaction": 420058.0,
    "paymentMethod": "upi",
    "status": "completed",
    "beneficiaryDetails": {
      "name": "Broadband",
      "bankName": "Unknown",
      "accountNumber": "N/A",
      "ifsc": "N/A"
    }
  },
  {
    "transactionId": "TXN100056",
    "accountNumber": "123456789012",
    "accountHolderName": "Rishikesh Negi",
    "transactionType": "debit",
    "amount": 8000.0,
    "date": "2025-09-10T11:00:00Z",
    "description": "Monthly house rent",
    "category": "rent",
    "balanceAfterTransaction": 412058.0,
    "paymentMethod": "bank_transfer",
    "status": "completed",
    "beneficiaryDetails": {
      "name": "Suresh Kumar (Landlord)",
      "bankName": "SBI",
      "accountNumber": "554433221100",
      "ifsc": "SBIN0000123"
    }
  },
  {
    "transactionId": "TXN100057",
    "accountNumber": "123456789012",
    "accountHolderName": "Rishikesh Negi",
    "transactionType": "debit",
    "amount": 4500.0,
    "date": "2025-09-15T14:00:00Z",
    "description": "Personal loan EMI",
    "category": "installment",
    "balanceAfterTransaction": 407558.0,
    "paymentMethod": "bank_transfer",
    "status": "completed",
    "beneficiaryDetails": {
      "name": "Bajaj Finance",
      "bankName": "Axis Bank",
      "accountNumber": "332211998877",
      "ifsc": "UTIB0000456"
    }
  },
  {
    "transactionId": "TXN100059",
    "accountNumber": "123456789012",
    "accountHolderName": "Rishikesh Negi",
    "transactionType": "debit",
    "amount": 11662.0,
    "date": "2025-09-25T00:00:00Z",
    "description": "Groww - Stock purchase",
    "category": "investment",
    "balanceAfterTransaction": 395896.0,
    "paymentMethod": "upi",
    "status": "completed",
    "beneficiaryDetails": {
      "name": "Groww",
      "bankName": "Unknown",
      "accountNumber": "N/A",
      "ifsc": "N/A"
    }
  },
  {
    "transactionId": "TXN100060",
    "accountNumber": "123456789012",
    "accountHolderName": "Rishikesh Negi",
    "transactionType": "debit",
    "amount": 2414.0,
    "date": "2025-09-27T00:00:00Z",
    "description": "Zomato order",
    "category": "food",
    "balanceAfterTransaction": 393482.0,
    "paymentMethod": "bank_transfer",
    "status": "completed",
    "beneficiaryDetails": {
      "name": "Zomato",
      "bankName": "Unknown",
      "accountNumber": "N/A",
      "ifsc": "N/A"
    }
  },
  {
    "transactionId": "TXN100061",
    "accountNumber": "123456789012",
    "accountHolderName": "Rishikesh Negi",
    "transactionType": "credit",
    "amount": 60000.0,
    "date": "2025-10-01T09:00:00Z",
    "description": "Monthly salary",
    "category": "salary",
    "balanceAfterTransaction": 453482.0,
    "paymentMethod": "bank_transfer",
    "status": "completed",
    "senderDetails": {
      "name": "Tech Corp Solutions",
      "bankName": "HDFC Bank",
      "accountNumber": "998877665544",
      "ifsc": "HDFC0001234"
    }
  },
  {
    "transactionId": "TXN100062",
    "accountNumber": "123456789012",
    "accountHolderName": "Rishikesh Negi",
    "transactionType": "debit",
    "amount": 8000.0,
    "date": "2025-10-10T11:00:00Z",
    "description": "Monthly house rent",
    "category": "rent",
    "balanceAfterTransaction": 445482.0,
    "paymentMethod": "bank_transfer",
    "status": "completed",
    "beneficiaryDetails": {
      "name": "Suresh Kumar (Landlord)",
      "bankName": "SBI",
      "accountNumber": "554433221100",
      "ifsc": "SBIN0000123"
    }
  },
  {
    "transactionId": "TXN100064",
    "accountNumber": "123456789012",
    "accountHolderName": "Rishikesh Negi",
    "transactionType": "debit",
    "amount": 3988.0,
    "date": "2025-10-13T00:00:00Z",
    "description": "Petrol pump refill",
    "category": "transit",
    "balanceAfterTransaction": 441494.0,
    "paymentMethod": "cheque",
    "status": "completed",
    "beneficiaryDetails": {
      "name": "Petrol",
      "bankName": "Unknown",
      "accountNumber": "N/A",
      "ifsc": "N/A"
    }
  },
  {
    "transactionId": "TXN100063",
    "accountNumber": "123456789012",
    "accountHolderName": "Rishikesh Negi",
    "transactionType": "debit",
    "amount": 4500.0,
    "date": "2025-10-15T14:00:00Z",
    "description": "Personal loan EMI",
    "category": "installment",
    "balanceAfterTransaction": 436994.0,
    "paymentMethod": "bank_transfer",
    "status": "completed",
    "beneficiaryDetails": {
      "name": "Bajaj Finance",
      "bankName": "Axis Bank",
      "accountNumber": "332211998877",
      "ifsc": "UTIB0000456"
    }
  },
  {
    "transactionId": "TXN100065",
    "accountNumber": "123456789012",
    "accountHolderName": "Rishikesh Negi",
    "transactionType": "debit",
    "amount": 2827.0,
    "date": "2025-10-17T00:00:00Z",
    "description": "Train ticket",
    "category": "transit",
    "balanceAfterTransaction": 434167.0,
    "paymentMethod": "cheque",
    "status": "completed",
    "beneficiaryDetails": {
      "name": "Train",
      "bankName": "Unknown",
      "accountNumber": "N/A",
      "ifsc": "N/A"
    }
  },
  {
    "transactionId": "TXN100066",
    "accountNumber": "123456789012",
    "accountHolderName": "Rishikesh Negi",
    "transactionType": "debit",
    "amount": 4074.0,
    "date": "2025-10-19T00:00:00Z",
    "description": "BigBasket",
    "category": "groceries",
    "balanceAfterTransaction": 430093.0,
    "paymentMethod": "cheque",
    "status": "completed",
    "beneficiaryDetails": {
      "name": "BigBasket",
      "bankName": "Unknown",
      "accountNumber": "N/A",
      "ifsc": "N/A"
    }
  },
  {
    "transactionId": "TXN100067",
    "accountNumber": "123456789012",
    "accountHolderName": "Rishikesh Negi",
    "transactionType": "debit",
    "amount": 11374.0,
    "date": "2025-10-28T00:00:00Z",
    "description": "Train ticket",
    "category": "transit",
    "balanceAfterTransaction": 418719.0,
    "paymentMethod": "upi",
    "status": "completed",
    "beneficiaryDetails": {
      "name": "Train",
      "bankName": "Unknown",
      "accountNumber": "N/A",
      "ifsc": "N/A"
    }
  },
  {
    "transactionId": "TXN100075",
    "accountNumber": "123456789012",
    "accountHolderName": "Rishikesh Negi",
    "transactionType": "debit",
    "amount": 3491.0,
    "date": "2025-11-01T00:00:00Z",
    "description": "Swiggy delivery",
    "category": "food",
    "balanceAfterTransaction": 415228.0,
    "paymentMethod": "upi",
    "status": "completed",
    "beneficiaryDetails": {
      "name": "Swiggy",
      "bankName": "Unknown",
      "accountNumber": "N/A",
      "ifsc": "N/A"
    }
  },
  {
    "transactionId": "TXN100070",
    "accountNumber": "123456789012",
    "accountHolderName": "Rishikesh Negi",
    "transactionType": "credit",
    "amount": 2743.0,
    "date": "2025-11-02T00:00:00Z",
    "description": "Dividend payout - Equity",
    "category": "dividend",
    "balanceAfterTransaction": 417971.0,
    "paymentMethod": "upi",
    "status": "completed",
    "senderDetails": {
      "name": "NSDL / CDSL",
      "bankName": "RBI",
      "accountNumber": "000011112222",
      "ifsc": "RBIS0000001"
    }
  },
  {
    "transactionId": "TXN100071",
    "accountNumber": "123456789012",
    "accountHolderName": "Rishikesh Negi",
    "transactionType": "debit",
    "amount": 4573.0,
    "date": "2025-11-04T00:00:00Z",
    "description": "Nike Store",
    "category": "shopping",
    "balanceAfterTransaction": 413398.0,
    "paymentMethod": "upi",
    "status": "completed",
    "beneficiaryDetails": {
      "name": "Nike",
      "bankName": "Unknown",
      "accountNumber": "N/A",
      "ifsc": "N/A"
    }
  },
  {
    "transactionId": "TXN100068",
    "accountNumber": "123456789012",
    "accountHolderName": "Rishikesh Negi",
    "transactionType": "credit",
    "amount": 60000.0,
    "date": "2025-11-05T09:00:00Z",
    "description": "Monthly salary",
    "category": "salary",
    "balanceAfterTransaction": 473398.0,
    "paymentMethod": "bank_transfer",
    "status": "completed",
    "senderDetails": {
      "name": "Tech Corp Solutions",
      "bankName": "HDFC Bank",
      "accountNumber": "998877665544",
      "ifsc": "HDFC0001234"
    }
  },
  {
    "transactionId": "TXN100069",
    "accountNumber": "123456789012",
    "accountHolderName": "Rishikesh Negi",
    "transactionType": "debit",
    "amount": 8000.0,
    "date": "2025-11-08T11:00:00Z",
    "description": "Monthly house rent",
    "category": "rent",
    "balanceAfterTransaction": 465398.0,
    "paymentMethod": "bank_transfer",
    "status": "completed",
    "beneficiaryDetails": {
      "name": "Suresh Kumar (Landlord)",
      "bankName": "SBI",
      "accountNumber": "554433221100",
      "ifsc": "SBIN0000123"
    }
  },
  {
    "transactionId": "TXN100074",
    "accountNumber": "123456789012",
    "accountHolderName": "Rishikesh Negi",
    "transactionType": "debit",
    "amount": 5396.0,
    "date": "2025-11-11T00:00:00Z",
    "description": "Petrol pump refill",
    "category": "transit",
    "balanceAfterTransaction": 460002.0,
    "paymentMethod": "bank_transfer",
    "status": "completed",
    "beneficiaryDetails": {
      "name": "Petrol",
      "bankName": "Unknown",
      "accountNumber": "N/A",
      "ifsc": "N/A"
    }
  },
  {
    "transactionId": "TXN100073",
    "accountNumber": "123456789012",
    "accountHolderName": "Rishikesh Negi",
    "transactionType": "credit",
    "amount": 1428.0,
    "date": "2025-11-25T00:00:00Z",
    "description": "Dividend payout - Equity",
    "category": "dividend",
    "balanceAfterTransaction": 461430.0,
    "paymentMethod": "upi",
    "status": "completed",
    "senderDetails": {
      "name": "NSDL / CDSL",
      "bankName": "RBI",
      "accountNumber": "000011112222",
      "ifsc": "RBIS0000001"
    }
  },
  {
    "transactionId": "TXN100072",
    "accountNumber": "123456789012",
    "accountHolderName": "Rishikesh Negi",
    "transactionType": "debit",
    "amount": 14645.0,
    "date": "2025-11-26T00:00:00Z",
    "description": "Spotify Premium",
    "category": "subscription",
    "balanceAfterTransaction": 446785.0,
    "paymentMethod": "cheque",
    "status": "completed",
    "beneficiaryDetails": {
      "name": "Spotify",
      "bankName": "Unknown",
      "accountNumber": "N/A",
      "ifsc": "N/A"
    }
  },
  {
    "transactionId": "TXN100076",
    "accountNumber": "123456789012",
    "accountHolderName": "Rishikesh Negi",
    "transactionType": "credit",
    "amount": 60000.0,
    "date": "2025-12-01T09:00:00Z",
    "description": "Monthly salary",
    "category": "salary",
    "balanceAfterTransaction": 506785.0,
    "paymentMethod": "bank_transfer",
    "status": "completed",
    "senderDetails": {
      "name": "Tech Corp Solutions",
      "bankName": "HDFC Bank",
      "accountNumber": "998877665544",
      "ifsc": "HDFC0001234"
    }
  },
  {
    "transactionId": "TXN100077",
    "accountNumber": "123456789012",
    "accountHolderName": "Rishikesh Negi",
    "transactionType": "debit",
    "amount": 8000.0,
    "date": "2025-12-05T11:00:00Z",
    "description": "Monthly house rent",
    "category": "rent",
    "balanceAfterTransaction": 498785.0,
    "paymentMethod": "bank_transfer",
    "status": "completed",
    "beneficiaryDetails": {
      "name": "Suresh Kumar (Landlord)",
      "bankName": "SBI",
      "accountNumber": "554433221100",
      "ifsc": "SBIN0000123"
    }
  },
  {
    "transactionId": "TXN100079",
    "accountNumber": "123456789012",
    "accountHolderName": "Rishikesh Negi",
    "transactionType": "debit",
    "amount": 248.0,
    "date": "2025-12-09T00:00:00Z",
    "description": "Local Kirana Store",
    "category": "groceries",
    "balanceAfterTransaction": 498537.0,
    "paymentMethod": "bank_transfer",
    "status": "completed",
    "beneficiaryDetails": {
      "name": "Local",
      "bankName": "Unknown",
      "accountNumber": "N/A",
      "ifsc": "N/A"
    }
  },
  {
    "transactionId": "TXN100082",
    "accountNumber": "123456789012",
    "accountHolderName": "Rishikesh Negi",
    "transactionType": "debit",
    "amount": 5739.0,
    "date": "2025-12-09T00:00:00Z",
    "description": "Mobile Recharge",
    "category": "bill",
    "balanceAfterTransaction": 492798.0,
    "paymentMethod": "bank_transfer",
    "status": "completed",
    "beneficiaryDetails": {
      "name": "Mobile",
      "bankName": "Unknown",
      "accountNumber": "N/A",
      "ifsc": "N/A"
    }
  },
  {
    "transactionId": "TXN100078",
    "accountNumber": "123456789012",
    "accountHolderName": "Rishikesh Negi",
    "transactionType": "debit",
    "amount": 2525.0,
    "date": "2025-12-15T00:00:00Z",
    "description": "BigBasket",
    "category": "groceries",
    "balanceAfterTransaction": 490273.0,
    "paymentMethod": "bank_transfer",
    "status": "completed",
    "beneficiaryDetails": {
      "name": "BigBasket",
      "bankName": "Unknown",
      "accountNumber": "N/A",
      "ifsc": "N/A"
    }
  },
  {
    "transactionId": "TXN100081",
    "accountNumber": "123456789012",
    "accountHolderName": "Rishikesh Negi",
    "transactionType": "debit",
    "amount": 4825.0,
    "date": "2025-12-16T00:00:00Z",
    "description": "Local Kirana Store",
    "category": "groceries",
    "balanceAfterTransaction": 485448.0,
    "paymentMethod": "cheque",
    "status": "completed",
    "beneficiaryDetails": {
      "name": "Local",
      "bankName": "Unknown",
      "accountNumber": "N/A",
      "ifsc": "N/A"
    }
  },
  {
    "transactionId": "TXN100080",
    "accountNumber": "123456789012",
    "accountHolderName": "Rishikesh Negi",
    "transactionType": "debit",
    "amount": 9568.0,
    "date": "2025-12-18T00:00:00Z",
    "description": "Reliance Fresh",
    "category": "groceries",
    "balanceAfterTransaction": 475880.0,
    "paymentMethod": "bank_transfer",
    "status": "completed",
    "beneficiaryDetails": {
      "name": "Reliance",
      "bankName": "Unknown",
      "accountNumber": "N/A",
      "ifsc": "N/A"
    }
  },
  {
    "transactionId": "TXN100083",
    "accountNumber": "123456789012",
    "accountHolderName": "Rishikesh Negi",
    "transactionType": "credit",
    "amount": 60000.0,
    "date": "2026-01-01T09:00:00Z",
    "description": "Monthly salary",
    "category": "salary",
    "balanceAfterTransaction": 535880.0,
    "paymentMethod": "bank_transfer",
    "status": "completed",
    "senderDetails": {
      "name": "Tech Corp Solutions",
      "bankName": "HDFC Bank",
      "accountNumber": "998877665544",
      "ifsc": "HDFC0001234"
    }
  },
  {
    "transactionId": "TXN100089",
    "accountNumber": "123456789012",
    "accountHolderName": "Rishikesh Negi",
    "transactionType": "credit",
    "amount": 1833.0,
    "date": "2026-01-04T00:00:00Z",
    "description": "Dividend payout - Equity",
    "category": "dividend",
    "balanceAfterTransaction": 537713.0,
    "paymentMethod": "bank_transfer",
    "status": "completed",
    "senderDetails": {
      "name": "NSDL / CDSL",
      "bankName": "RBI",
      "accountNumber": "000011112222",
      "ifsc": "RBIS0000001"
    }
  },
  {
    "transactionId": "TXN100084",
    "accountNumber": "123456789012",
    "accountHolderName": "Rishikesh Negi",
    "transactionType": "debit",
    "amount": 8000.0,
    "date": "2026-01-06T11:00:00Z",
    "description": "Monthly house rent",
    "category": "rent",
    "balanceAfterTransaction": 529713.0,
    "paymentMethod": "bank_transfer",
    "status": "completed",
    "beneficiaryDetails": {
      "name": "Suresh Kumar (Landlord)",
      "bankName": "SBI",
      "accountNumber": "554433221100",
      "ifsc": "SBIN0000123"
    }
  },
  {
    "transactionId": "TXN100085",
    "accountNumber": "123456789012",
    "accountHolderName": "Rishikesh Negi",
    "transactionType": "debit",
    "amount": 11507.0,
    "date": "2026-01-12T00:00:00Z",
    "description": "Dinner at Social",
    "category": "food",
    "balanceAfterTransaction": 518206.0,
    "paymentMethod": "bank_transfer",
    "status": "completed",
    "beneficiaryDetails": {
      "name": "Dinner",
      "bankName": "Unknown",
      "accountNumber": "N/A",
      "ifsc": "N/A"
    }
  },
  {
    "transactionId": "TXN100086",
    "accountNumber": "123456789012",
    "accountHolderName": "Rishikesh Negi",
    "transactionType": "debit",
    "amount": 9065.0,
    "date": "2026-01-14T00:00:00Z",
    "description": "Mobile Recharge",
    "category": "bill",
    "balanceAfterTransaction": 509141.0,
    "paymentMethod": "bank_transfer",
    "status": "completed",
    "beneficiaryDetails": {
      "name": "Mobile",
      "bankName": "Unknown",
      "accountNumber": "N/A",
      "ifsc": "N/A"
    }
  },
  {
    "transactionId": "TXN100087",
    "accountNumber": "123456789012",
    "accountHolderName": "Rishikesh Negi",
    "transactionType": "debit",
    "amount": 3311.0,
    "date": "2026-01-17T00:00:00Z",
    "description": "Swiggy delivery",
    "category": "food",
    "balanceAfterTransaction": 505830.0,
    "paymentMethod": "bank_transfer",
    "status": "completed",
    "beneficiaryDetails": {
      "name": "Swiggy",
      "bankName": "Unknown",
      "accountNumber": "N/A",
      "ifsc": "N/A"
    }
  },
  {
    "transactionId": "TXN100088",
    "accountNumber": "123456789012",
    "accountHolderName": "Rishikesh Negi",
    "transactionType": "debit",
    "amount": 10365.0,
    "date": "2026-01-24T00:00:00Z",
    "description": "iCloud Storage",
    "category": "subscription",
    "balanceAfterTransaction": 495465.0,
    "paymentMethod": "cheque",
    "status": "completed",
    "beneficiaryDetails": {
      "name": "iCloud",
      "bankName": "Unknown",
      "accountNumber": "N/A",
      "ifsc": "N/A"
    }
  },
  {
    "transactionId": "TXN100090",
    "accountNumber": "123456789012",
    "accountHolderName": "Rishikesh Negi",
    "transactionType": "debit",
    "amount": 12029.0,
    "date": "2026-01-24T00:00:00Z",
    "description": "Swiggy delivery",
    "category": "food",
    "balanceAfterTransaction": 483436.0,
    "paymentMethod": "cheque",
    "status": "completed",
    "beneficiaryDetails": {
      "name": "Swiggy",
      "bankName": "Unknown",
      "accountNumber": "N/A",
      "ifsc": "N/A"
    }
  },
  {
    "transactionId": "TXN100091",
    "accountNumber": "123456789012",
    "accountHolderName": "Rishikesh Negi",
    "transactionType": "credit",
    "amount": 60000.0,
    "date": "2026-02-02T09:00:00Z",
    "description": "Monthly salary",
    "category": "salary",
    "balanceAfterTransaction": 543436.0,
    "paymentMethod": "bank_transfer",
    "status": "completed",
    "senderDetails": {
      "name": "Tech Corp Solutions",
      "bankName": "HDFC Bank",
      "accountNumber": "998877665544",
      "ifsc": "HDFC0001234"
    }
  },
  {
    "transactionId": "TXN100096",
    "accountNumber": "123456789012",
    "accountHolderName": "Rishikesh Negi",
    "transactionType": "debit",
    "amount": 1823.0,
    "date": "2026-02-03T00:00:00Z",
    "description": "Myntra order",
    "category": "shopping",
    "balanceAfterTransaction": 541613.0,
    "paymentMethod": "bank_transfer",
    "status": "completed",
    "beneficiaryDetails": {
      "name": "Myntra",
      "bankName": "Unknown",
      "accountNumber": "N/A",
      "ifsc": "N/A"
    }
  },
  {
    "transactionId": "TXN100095",
    "accountNumber": "123456789012",
    "accountHolderName": "Rishikesh Negi",
    "transactionType": "debit",
    "amount": 10044.0,
    "date": "2026-02-10T00:00:00Z",
    "description": "Cafe coffee day",
    "category": "food",
    "balanceAfterTransaction": 531569.0,
    "paymentMethod": "upi",
    "status": "completed",
    "beneficiaryDetails": {
      "name": "Cafe",
      "bankName": "Unknown",
      "accountNumber": "N/A",
      "ifsc": "N/A"
    }
  },
  {
    "transactionId": "TXN100092",
    "accountNumber": "123456789012",
    "accountHolderName": "Rishikesh Negi",
    "transactionType": "debit",
    "amount": 8000.0,
    "date": "2026-02-10T11:00:00Z",
    "description": "Monthly house rent",
    "category": "rent",
    "balanceAfterTransaction": 523569.0,
    "paymentMethod": "bank_transfer",
    "status": "completed",
    "beneficiaryDetails": {
      "name": "Suresh Kumar (Landlord)",
      "bankName": "SBI",
      "accountNumber": "554433221100",
      "ifsc": "SBIN0000123"
    }
  },
  {
    "transactionId": "TXN100094",
    "accountNumber": "123456789012",
    "accountHolderName": "Rishikesh Negi",
    "transactionType": "debit",
    "amount": 14247.0,
    "date": "2026-02-15T00:00:00Z",
    "description": "Dinner at Social",
    "category": "food",
    "balanceAfterTransaction": 509322.0,
    "paymentMethod": "bank_transfer",
    "status": "completed",
    "beneficiaryDetails": {
      "name": "Dinner",
      "bankName": "Unknown",
      "accountNumber": "N/A",
      "ifsc": "N/A"
    }
  },
  {
    "transactionId": "TXN100093",
    "accountNumber": "123456789012",
    "accountHolderName": "Rishikesh Negi",
    "transactionType": "debit",
    "amount": 8826.0,
    "date": "2026-02-16T00:00:00Z",
    "description": "iCloud Storage",
    "category": "subscription",
    "balanceAfterTransaction": 500496.0,
    "paymentMethod": "cheque",
    "status": "completed",
    "beneficiaryDetails": {
      "name": "iCloud",
      "bankName": "Unknown",
      "accountNumber": "N/A",
      "ifsc": "N/A"
    }
  },
  {
    "transactionId": "TXN100097",
    "accountNumber": "123456789012",
    "accountHolderName": "Rishikesh Negi",
    "transactionType": "credit",
    "amount": 60000.0,
    "date": "2026-03-01T09:00:00Z",
    "description": "Monthly salary",
    "category": "salary",
    "balanceAfterTransaction": 560496.0,
    "paymentMethod": "bank_transfer",
    "status": "completed",
    "senderDetails": {
      "name": "Tech Corp Solutions",
      "bankName": "HDFC Bank",
      "accountNumber": "998877665544",
      "ifsc": "HDFC0001234"
    }
  },
  {
    "transactionId": "TXN100098",
    "accountNumber": "123456789012",
    "accountHolderName": "Rishikesh Negi",
    "transactionType": "debit",
    "amount": 8000.0,
    "date": "2026-03-08T11:00:00Z",
    "description": "Monthly house rent",
    "category": "rent",
    "balanceAfterTransaction": 552496.0,
    "paymentMethod": "bank_transfer",
    "status": "completed",
    "beneficiaryDetails": {
      "name": "Suresh Kumar (Landlord)",
      "bankName": "SBI",
      "accountNumber": "554433221100",
      "ifsc": "SBIN0000123"
    }
  },
  {
    "transactionId": "TXN100101",
    "accountNumber": "123456789012",
    "accountHolderName": "Rishikesh Negi",
    "transactionType": "debit",
    "amount": 14744.0,
    "date": "2026-03-11T00:00:00Z",
    "description": "Amazon.in",
    "category": "shopping",
    "balanceAfterTransaction": 537752.0,
    "paymentMethod": "cheque",
    "status": "completed",
    "beneficiaryDetails": {
      "name": "Amazon.in",
      "bankName": "Unknown",
      "accountNumber": "N/A",
      "ifsc": "N/A"
    }
  },
  {
    "transactionId": "TXN100103",
    "accountNumber": "123456789012",
    "accountHolderName": "Rishikesh Negi",
    "transactionType": "debit",
    "amount": 5502.0,
    "date": "2026-03-16T00:00:00Z",
    "description": "Nike Store",
    "category": "shopping",
    "balanceAfterTransaction": 532250.0,
    "paymentMethod": "cheque",
    "status": "completed",
    "beneficiaryDetails": {
      "name": "Nike",
      "bankName": "Unknown",
      "accountNumber": "N/A",
      "ifsc": "N/A"
    }
  },
  {
    "transactionId": "TXN100099",
    "accountNumber": "123456789012",
    "accountHolderName": "Rishikesh Negi",
    "transactionType": "debit",
    "amount": 4017.0,
    "date": "2026-03-17T00:00:00Z",
    "description": "Myntra order",
    "category": "shopping",
    "balanceAfterTransaction": 528233.0,
    "paymentMethod": "bank_transfer",
    "status": "completed",
    "beneficiaryDetails": {
      "name": "Myntra",
      "bankName": "Unknown",
      "accountNumber": "N/A",
      "ifsc": "N/A"
    }
  },
  {
    "transactionId": "TXN100100",
    "accountNumber": "123456789012",
    "accountHolderName": "Rishikesh Negi",
    "transactionType": "debit",
    "amount": 13956.0,
    "date": "2026-03-17T00:00:00Z",
    "description": "Broadband Bill",
    "category": "bill",
    "balanceAfterTransaction": 514277.0,
    "paymentMethod": "upi",
    "status": "completed",
    "beneficiaryDetails": {
      "name": "Broadband",
      "bankName": "Unknown",
      "accountNumber": "N/A",
      "ifsc": "N/A"
    }
  },
  {
    "transactionId": "TXN100104",
    "accountNumber": "123456789012",
    "accountHolderName": "Rishikesh Negi",
    "transactionType": "debit",
    "amount": 3713.0,
    "date": "2026-03-22T00:00:00Z",
    "description": "Electricity Bill",
    "category": "bill",
    "balanceAfterTransaction": 510564.0,
    "paymentMethod": "upi",
    "status": "completed",
    "beneficiaryDetails": {
      "name": "Electricity",
      "bankName": "Unknown",
      "accountNumber": "N/A",
      "ifsc": "N/A"
    }
  },
  {
    "transactionId": "TXN100102",
    "accountNumber": "123456789012",
    "accountHolderName": "Rishikesh Negi",
    "transactionType": "debit",
    "amount": 2073.0,
    "date": "2026-03-24T00:00:00Z",
    "description": "Dinner at Social",
    "category": "food",
    "balanceAfterTransaction": 508491.0,
    "paymentMethod": "cheque",
    "status": "completed",
    "beneficiaryDetails": {
      "name": "Dinner",
      "bankName": "Unknown",
      "accountNumber": "N/A",
      "ifsc": "N/A"
    }
  },
  {
    "transactionId": "TXN100105",
    "accountNumber": "123456789012",
    "accountHolderName": "Rishikesh Negi",
    "transactionType": "credit",
    "amount": 60000.0,
    "date": "2026-04-02T09:00:00Z",
    "description": "Monthly salary",
    "category": "salary",
    "balanceAfterTransaction": 568491.0,
    "paymentMethod": "bank_transfer",
    "status": "completed",
    "senderDetails": {
      "name": "Tech Corp Solutions",
      "bankName": "HDFC Bank",
      "accountNumber": "998877665544",
      "ifsc": "HDFC0001234"
    }
  },
  {
    "transactionId": "TXN100106",
    "accountNumber": "123456789012",
    "accountHolderName": "Rishikesh Negi",
    "transactionType": "debit",
    "amount": 8000.0,
    "date": "2026-04-08T11:00:00Z",
    "description": "Monthly house rent",
    "category": "rent",
    "balanceAfterTransaction": 560491.0,
    "paymentMethod": "bank_transfer",
    "status": "completed",
    "beneficiaryDetails": {
      "name": "Suresh Kumar (Landlord)",
      "bankName": "SBI",
      "accountNumber": "554433221100",
      "ifsc": "SBIN0000123"
    }
  },
  {
    "transactionId": "TXN100108",
    "accountNumber": "123456789012",
    "accountHolderName": "Rishikesh Negi",
    "transactionType": "debit",
    "amount": 12722.0,
    "date": "2026-04-09T00:00:00Z",
    "description": "Nike Store",
    "category": "shopping",
    "balanceAfterTransaction": 547769.0,
    "paymentMethod": "cheque",
    "status": "completed",
    "beneficiaryDetails": {
      "name": "Nike",
      "bankName": "Unknown",
      "accountNumber": "N/A",
      "ifsc": "N/A"
    }
  },
  {
    "transactionId": "TXN100107",
    "accountNumber": "123456789012",
    "accountHolderName": "Rishikesh Negi",
    "transactionType": "debit",
    "amount": 2135.0,
    "date": "2026-04-12T00:00:00Z",
    "description": "iCloud Storage",
    "category": "subscription",
    "balanceAfterTransaction": 545634.0,
    "paymentMethod": "bank_transfer",
    "status": "completed",
    "beneficiaryDetails": {
      "name": "iCloud",
      "bankName": "Unknown",
      "accountNumber": "N/A",
      "ifsc": "N/A"
    }
  },
  {
    "transactionId": "TXN100109",
    "accountNumber": "123456789012",
    "accountHolderName": "Rishikesh Negi",
    "transactionType": "debit",
    "amount": 9266.0,
    "date": "2026-04-12T00:00:00Z",
    "description": "Netflix monthly",
    "category": "subscription",
    "balanceAfterTransaction": 536368.0,
    "paymentMethod": "cheque",
    "status": "completed",
    "beneficiaryDetails": {
      "name": "Netflix",
      "bankName": "Unknown",
      "accountNumber": "N/A",
      "ifsc": "N/A"
    }
  },
  {
    "transactionId": "TXN100110",
    "accountNumber": "123456789012",
    "accountHolderName": "Rishikesh Negi",
    "transactionType": "debit",
    "amount": 4905.0,
    "date": "2026-04-24T00:00:00Z",
    "description": "Netflix monthly",
    "category": "subscription",
    "balanceAfterTransaction": 531463.0,
    "paymentMethod": "upi",
    "status": "completed",
    "beneficiaryDetails": {
      "name": "Netflix",
      "bankName": "Unknown",
      "accountNumber": "N/A",
      "ifsc": "N/A"
    }
  }
]
